LICENSE
README.md
setup.py
gitdir/__init__.py
gitdir/__main__.py
gitdir/gitdir.py
gitdir.egg-info/PKG-INFO
gitdir.egg-info/SOURCES.txt
gitdir.egg-info/dependency_links.txt
gitdir.egg-info/entry_points.txt
gitdir.egg-info/requires.txt
gitdir.egg-info/top_level.txt