Metadata-Version: 2.1
Name: gitdir
Version: 1.2.6
Summary: Download a single directory/folder from a GitHub repo
Home-page: https://github.com/sdushantha/gitdir
Author: Siddharth Dushantha
Author-email: siddharth.dushantha@gmail.com
License: UNKNOWN
Platform: UNKNOWN
License-File: LICENSE
